streamdown/__init__.py
streamdown/qwen3.md
streamdown/sd.py
streamdown/ss
streamdown/ss1
streamdown/test.txt
streamdown/plugins/README.md
streamdown/plugins/latex.py
streamdown-0.35.0.dist-info/METADATA
streamdown-0.35.0.dist-info/WHEEL
streamdown-0.35.0.dist-info/entry_points.txt
streamdown-0.35.0.dist-info/licenses/LICENSE.MIT
streamdown-0.35.0.dist-info/RECORD
