Metadata-Version: 2.4
Name: streamdown
Version: 0.35.0
Summary: A streaming markdown renderer for modern terminals with syntax highlighting
Project-URL: Homepage, https://github.com/day50-dev/Streamdown
Project-URL: Bug Tracker, https://github.com/day50-dev/Streamdown/issues
Author-email: Chris McKenzie <kristopolous@yahoo.com>
License: MIT
License-File: LICENSE.MIT
Keywords: cli,markdown,renderer,syntax-highlighting,terminal
Classifier: Development Status :: 4 - Beta
Classifier: Environment :: Console
Classifier: Intended Audience :: Developers
Classifier: License :: OSI Approved :: MIT License
Classifier: Programming Language :: Python :: 3
Classifier: Programming Language :: Python :: 3.8
Classifier: Programming Language :: Python :: 3.9
Classifier: Programming Language :: Python :: 3.10
Classifier: Programming Language :: Python :: 3.11
Classifier: Topic :: Text Processing :: Markup
Classifier: Topic :: Utilities
Requires-Python: >=3.8
Requires-Dist: appdirs
Requires-Dist: pygments
Requires-Dist: pylatexenc
Requires-Dist: term-image
Requires-Dist: toml
Requires-Dist: wcwidth
